{
  "module": "psspy",
  "function_name": "gettspfprofilecountbyelement",
  "category": "Multiple Element Data",
  "description": "Use this API to return the number of Time Series Power Flow profile by element name. This API routine was first introduced in release 35.4.0. ierr, count = gettspfprofilecountbyelement(element)",
  "python_syntax": "ierr, count = gettspfprofilecountbyelement(element)",
  "return_type": "error_and_count",
  "parameters": [
    {
      "name": "element",
      "description": "Name of the element that profiles will be returned. (input; no default allowed)."
    }
  ],
  "return_values": [
    {
      "name": "ierr",
      "description": "The error code . (output)."
    },
    {
      "name": "count",
      "description": "Number of time series power flow profile that defined for element. (output)."
    }
  ],
  "error_codes": [
    {
      "value": "= 0",
      "description": "No error; ‘COUNT’ returned."
    },
    {
      "value": "= 1",
      "description": "Curveid not found; ‘COUNT’ unchanged."
    }
  ]
}